ssoss/__init__.py
ssoss/dynamic_road_object.py
ssoss/motion_road_object.py
ssoss/process_road_objects.py
ssoss/process_video.py
ssoss/ssoss_cli.py
ssoss/ssoss_gui.py
ssoss/static_road_object.py
ssoss-0.5.1.dist-info/METADATA
ssoss-0.5.1.dist-info/WHEEL
ssoss-0.5.1.dist-info/licenses/LICENSE.txt
ssoss-0.5.1.dist-info/RECORD
