Metadata-Version: 2.1
Name: ssoss
Version: 0.5.1
Summary: Safe Sightings of Signs and Signals Package
Project-URL: Homepage, https://github.com/redmond2742/ssoss
Project-URL: Bug Tracker, https://github.com/redmond2742/ssoss/issues
Author-email: Matt Redmond <mr2742@gmail.com>
License-File: LICENSE.txt
Keywords: gpx,sight distance,traffic signals,video
Classifier: License :: OSI Approved :: MIT License
Classifier: Operating System :: OS Independent
Classifier: Programming Language :: Python :: 3
Requires-Python: >=3.9
Requires-Dist: geographiclib==2.0
Requires-Dist: geopy==2.4.0
Requires-Dist: gpxpy==1.5.0
Requires-Dist: imageio==2.31.5
Requires-Dist: lxml==4.9.3
Requires-Dist: numpy==1.26.0
Requires-Dist: opencv-python==4.8.1.78
Requires-Dist: pandas==2.1.1
Requires-Dist: pillow==10.0.1
Requires-Dist: python-dateutil==2.8.2
Requires-Dist: pytz==2023.3.post1
Requires-Dist: six==1.16.0
Requires-Dist: tqdm==4.66.1
Requires-Dist: tzdata==2023.3
